qalita_core/__init__.py
qalita_core/aggregation.py
qalita_core/data_source_opener.py
qalita_core/pack.py
qalita_core/pandas_sanitization.py
qalita_core/utils.py
qalita_core-1.4.1.dist-info/METADATA
qalita_core-1.4.1.dist-info/WHEEL
qalita_core-1.4.1.dist-info/licenses/LICENSE
qalita_core-1.4.1.dist-info/RECORD
