Metadata-Version: 2.4
Name: qalita_core
Version: 1.4.1
Summary: QALITA Platform Core lib for common function used in pack
Author-email: QALITA SAS <contact@qalita.io>
License-File: LICENSE
Classifier: Development Status :: 5 - Production/Stable
Classifier: Environment :: Console
Classifier: Intended Audience :: Developers
Classifier: Intended Audience :: Information Technology
Classifier: License :: Other/Proprietary License
Classifier: Natural Language :: English
Classifier: Operating System :: Unix
Classifier: Programming Language :: Python :: 3.10
Classifier: Programming Language :: Python :: 3.11
Classifier: Programming Language :: Python :: 3.12
Classifier: Topic :: Software Development :: Quality Assurance
Requires-Python: >=3.10
Requires-Dist: azure-storage-blob>=12.19.1
Requires-Dist: boto3>=1.34.81
Requires-Dist: google-cloud-storage>=2.16.0
Requires-Dist: hdfs>=2.7.3
Requires-Dist: openpyxl>=3.1.2
Requires-Dist: oracledb>=2.5.0
Requires-Dist: pandas>=2.2.0
Requires-Dist: paramiko>=3.4.0
Requires-Dist: psycopg2-binary>=2.9.9
Requires-Dist: pyarrow>=19.0.0
Requires-Dist: pymongo>=4.6.3
Requires-Dist: pymysql>=1.1.0
Requires-Dist: sqlalchemy>=2.0.27
Provides-Extra: dev
Requires-Dist: black>=23.3.0; extra == 'dev'
Requires-Dist: flake8<8.0,>=3.8.1; extra == 'dev'
Requires-Dist: pre-commit>=3.3.3; extra == 'dev'
Requires-Dist: pylint>=2.17.4; extra == 'dev'
Requires-Dist: pytest>=7.4.0; extra == 'dev'
